inara/__init__.py
inara/__main__.py
inara-0.1.1.dist-info/licenses/LICENSE
inara-0.1.1.dist-info/METADATA
inara-0.1.1.dist-info/WHEEL
inara-0.1.1.dist-info/top_level.txt
inara-0.1.1.dist-info/RECORD
