Metadata-Version: 2.4
Name: inara
Version: 0.1.1
Summary: Display Helpers in Jupyter, VSCode, and Databricks Notebooks for JSON and XML data. This is like IPython.display.JSON but also works in VSCode and Databricks.
Author-email: Philipp Thomann <philipp.thomann@d-one.ai>
License-Expression: Apache-2.0
Requires-Python: >=3.9.0
License-File: LICENSE
Provides-Extra: dev
Requires-Dist: build; extra == "dev"
Provides-Extra: all
Requires-Dist: pillow; extra == "all"
Dynamic: license-file
